PyLBFGS-0.2.0.16.dist-info/RECORD
PyLBFGS-0.2.0.16.dist-info/LICENSE
PyLBFGS-0.2.0.16.dist-info/WHEEL
PyLBFGS-0.2.0.16.dist-info/top_level.txt
PyLBFGS-0.2.0.16.dist-info/METADATA
lbfgs/__init__.py
lbfgs/_lowlevel.cpython-38-darwin.so
