Metadata-Version: 2.1
Name: PyLBFGS
Version: 0.2.0.16
Summary: LBFGS and OWL-QN optimization algorithms
Home-page: https://github.com/dedupeio/pylbfgs
Author: Lars Buitinck, Forest Gregg
Author-email: fgregg@gmail.com
License: UNKNOWN
Platform: UNKNOWN
Classifier: Intended Audience :: Developers
Classifier: Intended Audience :: Science/Research
Classifier: License :: OSI Approved :: MIT License
Classifier: Operating System :: POSIX
Classifier: Programming Language :: Cython
Classifier: Programming Language :: Python
Classifier: Topic :: Scientific/Engineering
Classifier: Topic :: Software Development
License-File: LICENSE
Requires-Dist: numpy (>=1.13.1)
